dm_core/__init__.py
dm_core/qdrant/__init__.py
dm_core/qdrant/service.py
dm_core/qdrant/tests/__init__.py
dm_core_qdrant-1.0.1.dist-info/licenses/LICENSE
dm_core_qdrant-1.0.1.dist-info/METADATA
dm_core_qdrant-1.0.1.dist-info/WHEEL
dm_core_qdrant-1.0.1.dist-info/top_level.txt
dm_core_qdrant-1.0.1.dist-info/RECORD
